healthstream/__init__.py
healthstream-0.0.1.dist-info/entry_points.txt
healthstream-0.0.1.dist-info/LICENSE
healthstream-0.0.1.dist-info/WHEEL
healthstream-0.0.1.dist-info/METADATA
healthstream-0.0.1.dist-info/RECORD
